mean_average_precision/__init__.py
mean_average_precision/adapter.py
mean_average_precision/mean_average_precision_2d.py
mean_average_precision/metric_base.py
mean_average_precision/metric_builder.py
mean_average_precision/multiprocessing.py
mean_average_precision/utils.py
mean_average_precision-2024.1.5.0.dist-info/LICENSE
mean_average_precision-2024.1.5.0.dist-info/METADATA
mean_average_precision-2024.1.5.0.dist-info/WHEEL
mean_average_precision-2024.1.5.0.dist-info/top_level.txt
mean_average_precision-2024.1.5.0.dist-info/zip-safe
mean_average_precision-2024.1.5.0.dist-info/RECORD
