Metadata-Version: 2.1
Name: mean-average-precision
Version: 2024.1.5.0
Summary: Mean Average Precision evaluator for object detection.
Home-page: https://github.com/bes-dev/mean_average_precision
Author: Sergei Belousov aka BeS
Author-email: sergei.o.belousov@gmail.com
License: MIT
Platform: UNKNOWN
Classifier: Programming Language :: Python :: 3
License-File: LICENSE
Requires-Dist: numpy
Requires-Dist: pandas
